beanstalkm/__about__.py
beanstalkm/__init__.py
beanstalkm/api.json
beanstalkm/message.json
beanstalkm-1.0.0.data/data/COPYRIGHT
beanstalkm-1.0.0.data/data/LICENSE
beanstalkm-1.0.0.dist-info/licenses/LICENSE
beanstalkm-1.0.0.dist-info/METADATA
beanstalkm-1.0.0.dist-info/WHEEL
beanstalkm-1.0.0.dist-info/top_level.txt
beanstalkm-1.0.0.dist-info/RECORD
